yusefs_library/__init__.py
yusefs_library/main.py
yusefs_library-0.2.dist-info/METADATA
yusefs_library-0.2.dist-info/WHEEL
yusefs_library-0.2.dist-info/entry_points.txt
yusefs_library-0.2.dist-info/top_level.txt
yusefs_library-0.2.dist-info/RECORD
