Metadata-Version: 2.1
Name: yusefs-library
Version: 0.2
Requires-Dist: numpy >=1.11.1
